_pynear.cpython-39-x86_64-linux-gnu.so
pynear-0.1.1.dist-info/WHEEL
pynear-0.1.1.dist-info/LICENSE
pynear-0.1.1.dist-info/top_level.txt
pynear-0.1.1.dist-info/RECORD
pynear-0.1.1.dist-info/METADATA
pynear/__init__.py
pynear/logging.py
pynear/_version.py
pynear/benchmark/__init__.py
pynear/benchmark/dataset.py
pynear/benchmark/run_benchmarks.py
pynear/benchmark/benchmark.py
pynear/benchmark/index_adapters.py
pynear/tests/__init__.py
pynear/tests/test_bktree.py
pynear/tests/test_serialization.py
pynear/tests/test_vptree.py
pynear.libs/libgomp-a34b3233.so.1.0.0
