Metadata-Version: 2.1
Name: pynear
Version: 0.1.1
Summary: An efficient implementation of Vantage Point Tree for Python 3
Home-page: https://github.com/pablocael/pynear
Author: Pablo Carneiro Elias
Author-email: pablo.cael@gmail.com
Requires-Python: >=3.7
License-File: LICENSE
Requires-Dist: numpy >=1.21.2
Provides-Extra: test
Requires-Dist: pytest >=6.0 ; extra == 'test'
